{
  "info": {
    "name": "AI Packaging Optimizer - Authentication",
    "description": "Authentication endpoints for the AI Packaging Optimizer API",
    "schema": "https://schema.getpostman.com/json/collection/v2.1.0/collection.json"
  },
  "variable": [
    {
      "key": "baseUrl",
      "value": "http://localhost:3000/api",
      "type": "string"
    },
    {
      "key": "accessToken",
      "value": "",
      "type": "string"
    },
    {
      "key": "refreshToken",
      "value": "",
      "type": "string"
    },
    {
      "key": "apiKey",
      "value": "",
      "type": "string"
    }
  ],
  "item": [
    {
      "name": "Register User",
      "request": {
        "method": "POST",
        "header": [
          {
            "key": "Content-Type",
            "value": "application/json"
          }
        ],
        "body": {
          "mode": "raw",
          "raw": "{\n  \"email\": \"test@example.com\",\n  \"password\": \"password123\",\n  \"role\": \"customer\"\n}"
        },
        "url": {
          "raw": "{{baseUrl}}/auth/register",
          "host": ["{{baseUrl}}"],
          "path": ["auth", "register"]
        },
        "description": "Register a new user account"
      },
      "response": []
    },
    {
      "name": "Login",
      "event": [
        {
          "listen": "test",
          "script": {
            "exec": [
              "if (pm.response.code === 200) {",
              "    const response = pm.response.json();",
              "    pm.collectionVariables.set('accessToken', response.data.accessToken);",
              "    pm.collectionVariables.set('refreshToken', response.data.refreshToken);",
              "}"
            ],
            "type": "text/javascript"
          }
        }
      ],
      "request": {
        "method": "POST",
        "header": [
          {
            "key": "Content-Type",
            "value": "application/json"
          }
        ],
        "body": {
          "mode": "raw",
          "raw": "{\n  \"email\": \"test@example.com\",\n  \"password\": \"password123\"\n}"
        },
        "url": {
          "raw": "{{baseUrl}}/auth/login",
          "host": ["{{baseUrl}}"],
          "path": ["auth", "login"]
        },
        "description": "Login with email and password to receive JWT tokens"
      },
      "response": []
    },
    {
      "name": "Refresh Token",
      "event": [
        {
          "listen": "test",
          "script": {
            "exec": [
              "if (pm.response.code === 200) {",
              "    const response = pm.response.json();",
              "    pm.collectionVariables.set('accessToken', response.data.accessToken);",
              "}"
            ],
            "type": "text/javascript"
          }
        }
      ],
      "request": {
        "method": "POST",
        "header": [
          {
            "key": "Content-Type",
            "value": "application/json"
          }
        ],
        "body": {
          "mode": "raw",
          "raw": "{\n  \"refreshToken\": \"{{refreshToken}}\"\n}"
        },
        "url": {
          "raw": "{{baseUrl}}/auth/refresh",
          "host": ["{{baseUrl}}"],
          "path": ["auth", "refresh"]
        },
        "description": "Refresh access token using refresh token"
      },
      "response": []
    },
    {
      "name": "Generate API Key",
      "event": [
        {
          "listen": "test",
          "script": {
            "exec": [
              "if (pm.response.code === 201) {",
              "    const response = pm.response.json();",
              "    pm.collectionVariables.set('apiKey', response.data.apiKey.key);",
              "}"
            ],
            "type": "text/javascript"
          }
        }
      ],
      "request": {
        "method": "POST",
        "header": [
          {
            "key": "Authorization",
            "value": "Bearer {{accessToken}}"
          }
        ],
        "url": {
          "raw": "{{baseUrl}}/auth/api-key",
          "host": ["{{baseUrl}}"],
          "path": ["auth", "api-key"]
        },
        "description": "Generate API key for authenticated user"
      },
      "response": []
    },
    {
      "name": "Logout",
      "request": {
        "method": "POST",
        "header": [
          {
            "key": "Authorization",
            "value": "Bearer {{accessToken}}"
          }
        ],
        "url": {
          "raw": "{{baseUrl}}/auth/logout",
          "host": ["{{baseUrl}}"],
          "path": ["auth", "logout"]
        },
        "description": "Logout authenticated user"
      },
      "response": []
    },
    {
      "name": "Test API Key Authentication",
      "request": {
        "method": "GET",
        "header": [
          {
            "key": "X-API-Key",
            "value": "{{apiKey}}"
          }
        ],
        "url": {
          "raw": "{{baseUrl}}/some-protected-endpoint",
          "host": ["{{baseUrl}}"],
          "path": ["some-protected-endpoint"]
        },
        "description": "Example of using API key for authentication"
      },
      "response": []
    }
  ]
}
